magicinpaint_cpu-1.0.2.data/purelib/magicinpaint.pyd
magicinpaint_cpu-1.0.2.dist-info/LICENSE
magicinpaint_cpu-1.0.2.dist-info/METADATA
magicinpaint_cpu-1.0.2.dist-info/WHEEL
magicinpaint_cpu-1.0.2.dist-info/top_level.txt
magicinpaint_cpu-1.0.2.dist-info/RECORD
