Metadata-Version: 2.1
Name: magicinpaint-cpu
Version: 1.0.2
Summary: Image Inpaint Library
Home-page: UNKNOWN
Author: Anton Milev
Author-email: amil@abv.bg
License: UNKNOWN
Platform: UNKNOWN
License-File: LICENSE
